MANIFEST.in
README.md
flake8_regex.py
setup.cfg
setup.py
flake8_regex.egg-info/PKG-INFO
flake8_regex.egg-info/SOURCES.txt
flake8_regex.egg-info/dependency_links.txt
flake8_regex.egg-info/entry_points.txt
flake8_regex.egg-info/not-zip-safe
flake8_regex.egg-info/pbr.json
flake8_regex.egg-info/top_level.txt