Metadata-Version: 1.1
Name: flake8-regex
Version: 0.3
Summary: Arbitrary regex checker, extension for flake8
Home-page: https://github.com/aristiden7o/flake8-regex
Author: Aristide Niyungeko
Author-email: aristide.niyungeko@gmail.com
License: GNU General Public License v2 (GPLv2)
Keywords: flake8 regex
Platform: UNKNOWN
Classifier: Development Status :: 3 - Alpha
Classifier: Environment :: Console
Classifier: Intended Audience :: Developers
Classifier: License :: OSI Approved :: GNU General Public License v2 (GPLv2)
Classifier: Operating System :: OS Independent
Classifier: Programming Language :: Python
Classifier: Programming Language :: Python :: 2
Classifier: Programming Language :: Python :: 3
Classifier: Topic :: Software Development :: Libraries :: Python Modules
Classifier: Topic :: Software Development :: Quality Assurance
